settrade_line_notify/__init__.py
settrade_line_notify/notification.py
settrade_line_notify-0.1.2.dist-info/METADATA
settrade_line_notify-0.1.2.dist-info/WHEEL
settrade_line_notify-0.1.2.dist-info/top_level.txt
settrade_line_notify-0.1.2.dist-info/RECORD
