Metadata-Version: 2.1
Name: settrade-line-notify
Version: 0.1.2
Summary: Simple Line Notify for supporting Settrade Open API Python SDK (and also any other general purposes)
Home-page: UNKNOWN
Author: Julapat Julnual
License: MIT
Platform: UNKNOWN
Requires-Dist: requests
